c3reference/__init__.py
c3reference/authserver.py
c3reference/beacon.py
c3reference/frame.py
c3reference/kafka.py
c3reference/listener.py
c3reference/protocol.py
c3reference/proto/__init__.py
c3reference/proto/common_pb2.py
c3reference/proto/location_pb2.py
c3reference/proto/management_pb2.py
c3_reference-2.0.1.dist-info/LICENSE
c3_reference-2.0.1.dist-info/METADATA
c3_reference-2.0.1.dist-info/WHEEL
c3_reference-2.0.1.dist-info/entry_points.txt
c3_reference-2.0.1.dist-info/top_level.txt
c3_reference-2.0.1.dist-info/RECORD
